{
  "n_neighbors": 10,
  "metric": "cosine",
  "n_occupations": 20,
  "n_skills": 38,
  "skills_list": [
    "3D Modeling",
    "AI/Deep Learning",
    "Adaptability",
    "Agile Methodologies",
    "Animation",
    "Business Analysis",
    "Cloud Computing",
    "Communication",
    "Creativity",
    "Critical Thinking",
    "Customer Service",
    "Cybersecurity",
    "Data Analysis",
    "Data Visualization",
    "Database Management",
    "Design",
    "HR Management",
    "Healthcare Knowledge",
    "Leadership",
    "Machine Learning",
    "Marketing",
    "Medical Diagnosis",
    "Mobile Development",
    "Patient Care",
    "Problem Solving",
    "Programming",
    "Project Management",
    "Remote Collaboration",
    "Renewable Energy",
    "Research",
    "Sales",
    "Statistical Analysis",
    "Sustainability",
    "Teamwork",
    "Technical Writing",
    "Time Management",
    "Video Editing",
    "Web Development"
  ],
  "future_job_rate": 51.600000000000016,
  "avg_growth": 17.205
}